xxj_nameko_dependency
