Metadata-Version: 2.1
Name: xxj-nameko-dependency
Version: 0.4
Summary: xxj nameko dependency
Home-page: UNKNOWN
Author: william.dai
Author-email: daixiang1992@gmail.com
License: MIT
Keywords: xxj nameko
Platform: UNKNOWN
